Workbook

Sheet Start here
A1: VerifiCasa — work plan
A2: Made 23 Oct 2026. Open 'Tasks', do the rows where Who = You, change Status from the dropdown. Claude does the rest next session.
A4: Progress | B4: Count
A5: Total tasks | B5: =COUNTA(Tasks!A2:A58) -> 17
A6: Done | B6: =COUNTIF(Tasks!F2:F58,"Done") -> 0
A7: Blocked | B7: =COUNTIF(Tasks!F2:F58,"Blocked") -> 0
A8: Open for You | B8: =COUNTIFS(Tasks!D2:D58,"You",Tasks!F2:F58,"<>Done") -> 7
A9: Open for Claude | B9: =COUNTIFS(Tasks!D2:D58,"Claude",Tasks!F2:F58,"<>Done") -> 8
A10: Open P0 (do now) | B10: =COUNTIFS(Tasks!E2:E58,"P0 – now",Tasks!F2:F58,"<>Done") -> 4
A11: % done | B11: =IF(B5=0,0,B6/B5) -> 0
A13: Tomorrow, in order
A14: 1. You: install Claude GitHub App on iamvava7 (T01)
A15: 2. You: add INTEGRATIONS_MASTER_KEY in Base44 (T04)
A16: 3. Claude: push SpaceTwin commits (T02)
A17: 4. Both: test admin panel in preview (T05)
A18: 5. You: answer 'Questions for you' tab
A20: Legend
A21: Yellow cells | B21: for you to fill in
A22: Blue numbers | B22: inputs you can change (Suggestions)
A23: Dropdowns | B23: Who / Priority / Status / Decision
A24: Green / red / yellow rows | B24: Done / Blocked / In progress
A25: Never write | B25: API keys or passwords in this file

Sheet Tasks
A1: ID | B1: Area | C1: Task | D1: Who | E1: Priority | F1: Status | G1: Depends on | H1: How / notes | I1: Done date
A2: T01 | B2: GitHub | C2: Install the Claude GitHub App on the iamvava7 account and give it the 'yes' repo | D2: You | E2: P0 – now | F2: To do | H2: Sign in as iamvava7 → github.com/apps/claude/installations/select_target → iamvava7 → repo 'yes'. If still blocked, start a new session with iamvava7/yes selected.
A3: T02 | B3: GitHub | C3: Push the 3 waiting SpaceTwin commits (tour page, tour quality, Maria) | D3: Claude | E3: P0 – now | F3: To do | G3: T01 | H3: Branch 'spacetwin'. Backup: spacetwin-unpushed.bundle (git pull <bundle> spacetwin).
A4: T03 | B4: GitHub | C4: Make repos private (if still wanted) | D4: You | E4: P2 – later | F4: To do | G4: T02 | H4: GitHub → repo → Settings → Danger zone → Change visibility. Testers then need an invite to clone.
A5: T04 | B5: Website | C5: Add the secret INTEGRATIONS_MASTER_KEY in Base44 | D5: You | E5: P0 – now | F5: To do | H5: Base44 → Settings → Secrets. Long random phrase (min 16 chars). Never share it or put it in the repo.
A6: T05 | B6: Website | C6: Test branch claude/admin-integrations-texts in Base44 preview | D6: Both | E6: P0 – now | F6: To do | G6: T04 | H6: Admin → 'Integrări & chei API': save + Test a Stripe key. Admin → 'Texte site': change one text, check it appears live, then 'Original'.
A7: T06 | B7: Website | C7: Merge claude/admin-integrations-texts into main | D7: Claude | E7: P1 – next | F7: To do | G7: T05 | H7: Only after your OK. Base44 publishes from main.
A8: T07 | B8: Maria AI | C8: Add the Anthropic API key so Maria uses Claude | D8: You | E8: P1 – next | F8: To do | G8: T02 | H8: console.anthropic.com → API key → set ANTHROPIC_API_KEY on the tour server (or in the new admin panel). Without it Maria still answers from listing facts.
A9: T08 | B9: Hosting | C9: Choose where the tour app (SpaceTwin) runs | D9: You | E9: P1 – next | F9: To do | H9: Needs Node + Python + OpenCV for the pro stitcher. Options: small VPS (Hetzner/DigitalOcean), Render, Fly.io.
A10: T09 | B10: Hosting | C10: Deploy SpaceTwin + connect it to verificasa.ro (/3D links) | D10: Claude | E10: P1 – next | F10: To do | G10: T02, T08 | H10: Set VERIFICASA env (app id), domain, HTTPS. Check embed iframe on a listing.
A11: T10 | B11: Capture | C11: Decide: phone only, or also a 360° camera (e.g. Insta360) | D11: You | E11: P1 – next | F11: To do | H11: Changes the capture flow; a 360° camera gives Teleport/Matterport-level quality fastest.
A12: T11 | B12: Capture | C12: Real-home test: capture 1 apartment with a phone, review quality | D12: Both | E12: P1 – next | F12: To do | G12: T09 | H12: Send me the result link; I tune stitching/exposure on real footage.
A13: T12 | B13: Website | C13: Fix Tur 3D page copy + add 'Tur 3D' search filter | D13: Claude | E13: P2 – later | F13: To do | G13: T06
A14: T13 | B14: Website | C14: Floor-plan tab on each listing | D14: Claude | E14: P2 – later | F14: To do | G14: T09
A15: T14 | B15: Website | C15: Energy class (CPE) + price/m² on listing cards | D15: Claude | E15: P2 – later | F15: To do | G15: T06 | H15: Law 372/2005 already requires the energy certificate.
A16: T15 | B16: Website | C16: 'Noua Casă' mortgage calculator | D16: Claude | E16: P2 – later | F16: To do | G16: T06 | H16: 2026 rules: 5% deposit ≤ €70k, 15% ≤ €140k — re-check before launch.
A17: T16 | B17: Website | C17: 'Verified on site' badge from GPS capture stamp | D17: Claude | E17: P1 – next | F17: To do | G17: T09 | H17: Backend already stores the capture stamp.
A18: T17 | B18: Figma | C18: Review the Figma tour viewer vs the built page and send changes | D18: You | E18: P2 – later | F18: To do | G18: T09 | H18: Figma page '🌐 Web · 3D Tour viewer'.

Sheet Done so far
A1: Repo | B1: Branch | C1: Commit | D1: What changed | E1: On GitHub?
A2: iamvava7/yes | B2: spacetwin | C2: a4ab7c1 | D2: Pro OpenCV stitcher (hides seams, no ghosting), VerifiCasa look, listing embed + /3D links | E2: Yes
A3: iamvava7/yes | B3: spacetwin | C3: 5a0b53a | D3: Tour page rebuilt from Figma 'Web · 3D Tour viewer' (PC + phone, details panel, room strip, loading) | E3: No – waiting T02
A4: iamvava7/yes | B4: spacetwin | C4: 6701ee7 | D4: Tour quality: sharper 360°, 2D plan with room sizes + wall lengths, dollhouse studio look, measure snapping, tiny-planet intro, labels; VerifiCasa listings in the app, verified-on-site stamp | E4: No – waiting T02
A5: iamvava7/yes | B5: spacetwin | C5: 984f06e | D5: Maria AI agent: only about this home, RO/EN, map card, go-to-room, call/WhatsApp/email, voice | E5: No – waiting T02
A6: vava6969/verificasa | B6: claude/admin-integrations-texts | C6: (latest) | D6: Admin 'Integrări & chei API' (encrypted keys, test, delete, custom) + 'Texte site' live editor (RO/EN) | E6: Yes – not merged
A7: vava6969/verificasa | B7: main | C7: (existing) | D7: Live Stripe price editing already exists: Admin → 'Planuri & Prețuri' | E7: —

Sheet Suggestions
A1: # | B1: Idea | C1: Why it helps (Romania) | D1: Inspired by | E1: Impact (1-5) | F1: Effort (1-5) | G1: Score | H1: Decision
A2: 1 | B2: Verified-on-site badge (GPS + date of capture) | C2: Fake listings are a big trust problem in Romanian portals | D2: Original (VerifiCasa) | E2: 5 | F2: 2 | G2: =E2*2-F2 -> 8
A3: 2 | B3: 'Tur 3D' filter + floor-plan tab | C3: Listings with tours/plans get more views and saves | D3: Zillow, Immoweb | E3: 5 | F3: 2 | G3: =E3*2-F3 -> 8
A4: 3 | B4: Energy class (CPE) + price/m² on cards | C4: Buyers compare by price/m²; CPE is legally required | D4: ImmoScout24 | E4: 4 | F4: 1 | G4: =E4*2-F4 -> 7
A5: 4 | B5: Seismic risk class field (Bucharest!) | C5: Seismic class is going into the land register; huge concern in Bucharest | D5: Original | E5: 5 | F5: 2 | G5: =E5*2-F5 -> 8
A6: 5 | B6: Noua Casă / mortgage calculator | C6: Most buyers finance; shows real monthly cost | D6: Zillow BuyAbility | E6: 4 | F6: 2 | G6: =E6*2-F6 -> 6
A7: 6 | B7: Neighbourhood layers: schools, metro, noise, parks | C7: Location is the #1 question; Maria can use it too | D7: Zoopla | E7: 4 | F7: 3 | G7: =E7*2-F7 -> 5
A8: 7 | B8: Agent dashboard: tour views, Maria chats, leads | C8: Proves value to agents → they bring listings | D8: Matterport, Zillow | E8: 4 | F8: 3 | G8: =E8*2-F8 -> 5
A9: 8 | B9: Saved searches + alerts (email/WhatsApp) | C9: Brings buyers back; WhatsApp is the main channel in RO | D9: Zillow, Storia | E9: 4 | F9: 2 | G9: =E9*2-F9 -> 6
A10: 9 | B10: Price history + 'days on market' | C10: Transparency; negotiation help | D10: Zillow | E10: 3 | F10: 2 | G10: =E10*2-F10 -> 4
A11: 10 | B11: Virtual staging (empty rooms furnished, clearly labeled) | C11: Empty flats sell worse; must be labeled to stay honest | D11: Zillow, Matterport | E11: 3 | F11: 4 | G11: =E11*2-F11 -> 2
A12: 11 | B12: Book a viewing slot from the tour | C12: Turns a tour into a meeting directly | D12: Zillow messaging | E12: 4 | F12: 2 | G12: =E12*2-F12 -> 6
A13: 12 | B13: Annotations / notes in the tour (e.g. 'new boiler 2024') | C13: Agents highlight value; builds trust | D13: Matterport Mattertags | E13: 3 | F13: 2 | G13: =E13*2-F13 -> 4
... A16: 15 | B16: Agency white-label tours (own logo) | C16: Paid feature for agencies → revenue | D16: Matterport | E16: 3 | F16: 2 | G16: =E16*2-F16 -> 4
B18: Score = Impact × 2 − Effort (higher = do first). Edit the blue numbers; pick a Decision from the list.

Sheet Questions for you
A1: # | B1: Question | C1: Your answer
A2: 1 | B2: Merge the admin branch into main after testing? (T06)
A3: 2 | B3: Do you have an Anthropic API key for Maria? (T07)
A4: 3 | B4: Phone only, or also a 360° camera? Which one? (T10)
A5: 4 | B5: Where should the tour app run (VPS / Render / Fly)? Budget per month? (T08)
A6: 5 | B6: Which suggestion first? (see Suggestions → Decision)
A7: 6 | B7: Still want all repos private? (T03)
